sphero_rvr_mcp/__init__.py
sphero_rvr_mcp/__main__.py
sphero_rvr_mcp/api.py
sphero_rvr_mcp/config.py
sphero_rvr_mcp/models.py
sphero_rvr_mcp/server.py
sphero_rvr_mcp/core/__init__.py
sphero_rvr_mcp/core/command_queue.py
sphero_rvr_mcp/core/exceptions.py
sphero_rvr_mcp/core/state_manager.py
sphero_rvr_mcp/hardware/__init__.py
sphero_rvr_mcp/hardware/connection_manager.py
sphero_rvr_mcp/hardware/safety_monitor.py
sphero_rvr_mcp/hardware/sensor_stream_manager.py
sphero_rvr_mcp/observability/__init__.py
sphero_rvr_mcp/observability/logging.py
sphero_rvr_mcp/protocol/__init__.py
sphero_rvr_mcp/protocol/commands.py
sphero_rvr_mcp/protocol/direct_serial.py
sphero_rvr_mcp/protocol/dispatcher.py
sphero_rvr_mcp/protocol/movement.py
sphero_rvr_mcp/protocol/packet.py
sphero_rvr_mcp/services/__init__.py
sphero_rvr_mcp/services/connection_service.py
sphero_rvr_mcp/services/ir_service.py
sphero_rvr_mcp/services/led_service.py
sphero_rvr_mcp/services/movement_service.py
sphero_rvr_mcp/services/safety_service.py
sphero_rvr_mcp/services/sensor_service.py
sphero_rvr_mcp/tools/__init__.py
sphero_rvr_mcp/tools/connection_tools.py
sphero_rvr_mcp/tools/ir_tools.py
sphero_rvr_mcp/tools/led_tools.py
sphero_rvr_mcp/tools/movement_tools.py
sphero_rvr_mcp/tools/safety_tools.py
sphero_rvr_mcp/tools/sensor_tools.py
sphero_rvr_mcp-0.2.5.dist-info/METADATA
sphero_rvr_mcp-0.2.5.dist-info/WHEEL
sphero_rvr_mcp-0.2.5.dist-info/entry_points.txt
sphero_rvr_mcp-0.2.5.dist-info/licenses/LICENSE
sphero_rvr_mcp-0.2.5.dist-info/RECORD
