Metadata-Version: 2.4
Name: sphero-rvr-mcp
Version: 0.2.5
Summary: MCP server for controlling Sphero RVR with Claude AI - featuring direct serial protocol for low-latency control
Project-URL: Homepage, https://github.com/jsperson/sphero_rvr_mcp
Project-URL: Repository, https://github.com/jsperson/sphero_rvr_mcp
Project-URL: Issues, https://github.com/jsperson/sphero_rvr_mcp/issues
Author-email: Jason Scott Person <jsperson+rvr@gmail.com>
License-Expression: MIT
License-File: LICENSE
Keywords: claude,mcp,model-context-protocol,raspberry-pi,robotics,rvr,sphero
Classifier: Development Status :: 4 - Beta
Classifier: Intended Audience :: Developers
Classifier: Intended Audience :: Education
Classifier: License :: OSI Approved :: MIT License
Classifier: Operating System :: POSIX :: Linux
Classifier: Programming Language :: Python :: 3
Classifier: Programming Language :: Python :: 3.10
Classifier: Programming Language :: Python :: 3.11
Classifier: Programming Language :: Python :: 3.12
Classifier: Topic :: Scientific/Engineering :: Artificial Intelligence
Classifier: Topic :: Software Development :: Libraries :: Python Modules
Requires-Python: >=3.10
Requires-Dist: fastmcp>=2.0.0
Requires-Dist: pydantic>=2.0.0
Requires-Dist: pyserial>=3.5
Requires-Dist: structlog>=24.1.0
Provides-Extra: dev
Requires-Dist: pytest-asyncio>=0.23.0; extra == 'dev'
Requires-Dist: pytest-timeout>=2.2.0; extra == 'dev'
Requires-Dist: pytest>=7.0.0; extra == 'dev'
